[
  {
    "Crossover": {
      "Probability": 0.05,
      "Type": 2
    },
    "Epochs": 100,
    "Mutator": {
      "MutateRatio": 0.1,
      "Type": 1
    },
    "OutputFileName": "LearningManager_hard_1_PartiallyMatchedCrossover_005_SwapMutator_01_Roulette_{0}.csv",
    "InputFileName": "ai-lab1-ttp_data/hard_1.ttp",
    "TestName": "Test hard 1 - Order, Swap, Tournament",
    "PopulationSize": 1000,
    "Selector": {
      "SpecimenCount": 5,
      "Type": 1,
      "IsMinimalizing": false
    },
    "SpecimenInitializator": {
      "ItemAddPropability": 0.3,
      "Type": 2
    },
    "RunCount": 1,
    "RunAsTask": true
  }
]