[
  {
    "Mutator": "Swap",
    "GreedyKnapsackMutator": true,
    "SpecimenInitializator": {
      "Type": "Greedy",
      "ItemAddPropability": 0.3
    },
    "NeighborhoodSize": 1,
    "AnnealingRate": 0.998,
    "StartingTemperature": 10000000,
    "TargetTemperature": 1,
    "TestName": "Medium0",
    "OutputFileName": "Output2/Medium0_1_2000.csv",
    "InputFileName": "ai-lab1-ttp_data/medium_0.ttp",
    "Iterations": 2000,
    "RunCount": 10
  },
  {
    "Mutator": "Swap",
    "GreedyKnapsackMutator": true,
    "SpecimenInitializator": {
      "Type": "Greedy",
      "ItemAddPropability": 0.3
    },
    "NeighborhoodSize": 1,
    "AnnealingRate": 0.999,
    "StartingTemperature": 10000000,
    "TargetTemperature": 1,
    "TestName": "Medium0",
    "OutputFileName": "Output2/Medium0_1_250000.csv",
    "InputFileName": "ai-lab1-ttp_data/medium_0.ttp",
    "Iterations": 250000,
    "RunCount": 10
  },
  {
    "Mutator": "Swap",
    "GreedyKnapsackMutator": true,
    "SpecimenInitializator": {
      "Type": "Greedy",
      "ItemAddPropability": 0.3
    },
    "NeighborhoodSize": 4,
    "AnnealingRate": 0.998,
    "StartingTemperature": 10000000,
    "TargetTemperature": 1,
    "TestName": "Medium0",
    "OutputFileName": "Output2/Medium0_4_2000.csv",
    "InputFileName": "ai-lab1-ttp_data/medium_0.ttp",
    "Iterations": 2000,
    "RunCount": 10
  },
  {
    "Mutator": "Swap",
    "GreedyKnapsackMutator": true,
    "SpecimenInitializator": {
      "Type": "Greedy",
      "ItemAddPropability": 0.3
    },
    "NeighborhoodSize": 10,
    "AnnealingRate": 0.998,
    "StartingTemperature": 10000000,
    "TargetTemperature": 1,
    "TestName": "Medium0",
    "OutputFileName": "Output2/Medium0_10_2000.csv",
    "InputFileName": "ai-lab1-ttp_data/medium_0.ttp",
    "Iterations": 2000,
    "RunCount": 10
  },

  {
    "Mutator": "Swap",
    "GreedyKnapsackMutator": true,
    "SpecimenInitializator": {
      "Type": "Greedy",
      "ItemAddPropability": 0.3
    },
    "NeighborhoodSize": 10,
    "AnnealingRate": 0.998,
    "StartingTemperature": 10000000,
    "TargetTemperature": 1,
    "TestName": "Hard0",
    "OutputFileName": "Output2/Hard0_10_6000.csv",
    "InputFileName": "ai-lab1-ttp_data/hard_0.ttp",
    "Iterations": 6000,
    "RunCount": 10
  },
  {
    "Mutator": "Swap",
    "GreedyKnapsackMutator": true,
    "SpecimenInitializator": {
      "Type": "Greedy",
      "ItemAddPropability": 0.3
    },
    "NeighborhoodSize": 4,
    "AnnealingRate": 0.998,
    "StartingTemperature": 10000000,
    "TargetTemperature": 1,
    "TestName": "Medium0",
    "OutputFileName": "Output2/Medium0_4_4000.csv",
    "InputFileName": "ai-lab1-ttp_data/medium_0.ttp",
    "Iterations": 4000,
    "RunCount": 10
  },
  {
    "Mutator": "Swap",
    "GreedyKnapsackMutator": true,
    "SpecimenInitializator": {
      "Type": "Greedy",
      "ItemAddPropability": 0.3
    },
    "NeighborhoodSize": 4,
    "AnnealingRate": 0.998,
    "StartingTemperature": 10000000,
    "TargetTemperature": 1,
    "TestName": "Medium0",
    "OutputFileName": "Output2/Medium0_4_6000.csv",
    "InputFileName": "ai-lab1-ttp_data/medium_0.ttp",
    "Iterations": 6000,
    "RunCount": 10
  }
]